{
  "index": [
    {
      "id": "21a0cd7520260127224554",
      "shard": "shard_1.json",
      "title": "Edge Computing: Dữ liệu gốc từ cổ tịch/papers",
      "category": "Công Nghệ Mới & Tương Lai",
      "tags": [
        "autonomous",
        "hyper-depth",
        "agent-14"
      ],
      "created_at": "2026-01-27T22:45:54.676186"
    },
    {
      "id": "0c5f114320260127224555",
      "shard": "shard_1.json",
      "title": "Robotics & Cybernetics: Hướng dẫn chi thực",
      "category": "Công Nghệ Mới & Tương Lai",
      "tags": [
        "autonomous",
        "hyper-depth",
        "agent-7"
      ],
      "created_at": "2026-01-27T22:45:55.000426"
    },
    {
      "id": "ce69a18b20260127224555",
      "shard": "shard_1.json",
      "title": "Robotics & Cybernetics: Case study hiếm",
      "category": "Công Nghệ Mới & Tương Lai",
      "tags": [
        "autonomous",
        "hyper-depth",
        "agent-33"
      ],
      "created_at": "2026-01-27T22:45:55.401994"
    },
    {
      "id": "e71e4a5b20260127224556",
      "shard": "shard_1.json",
      "title": "Web 4.0 & Blockchain: Dữ liệu gốc từ cổ tịch/papers",
      "category": "Công Nghệ Mới & Tương Lai",
      "tags": [
        "autonomous",
        "hyper-depth",
        "agent-11"
      ],
      "created_at": "2026-01-27T22:45:56.050770"
    },
    {
      "id": "5477f98a20260127224556",
      "shard": "shard_1.json",
      "title": "AI Ethics & Global Policy: Ví dụ thực tế 2026",
      "category": "Công Nghệ Mới & Tương Lai",
      "tags": [
        "autonomous",
        "hyper-depth",
        "agent-42"
      ],
      "created_at": "2026-01-27T22:45:56.541179"
    },
    {
      "id": "c19dbd4a20260128213919",
      "shard": "shard_1.json",
      "title": "Huyền Không Đại Quái: Ví dụ thực tế 2026",
      "category": "Kinh Dịch & Dự Đoán",
      "tags": [
        "autonomous",
        "hyper-depth",
        "agent-29"
      ],
      "created_at": "2026-01-28T21:39:19.230808"
    },
    {
      "id": "b0ec089e20260128213919",
      "shard": "shard_1.json",
      "title": "Tế lễ và Kinh Dịch: Bí quyết thực thi nhanh",
      "category": "Kinh Dịch & Dự Đoán",
      "tags": [
        "autonomous",
        "hyper-depth",
        "agent-12"
      ],
      "created_at": "2026-01-28T21:39:19.907352"
    },
    {
      "id": "44bcc20620260128213921",
      "shard": "shard_1.json",
      "title": "Kinh Dịch và tâm lý học hiện đại: Bí quyết thực thi nhanh",
      "category": "Kinh Dịch & Dự Đoán",
      "tags": [
        "autonomous",
        "hyper-depth",
        "agent-15"
      ],
      "created_at": "2026-01-28T21:39:21.956306"
    },
    {
      "id": "7d17ecb220260128213922",
      "shard": "shard_1.json",
      "title": "Ứng dụng Kinh Dịch trong tài chính: Ví dụ thực tế 2026",
      "category": "Kinh Dịch & Dự Đoán",
      "tags": [
        "autonomous",
        "hyper-depth",
        "agent-10"
      ],
      "created_at": "2026-01-28T21:39:22.669877"
    },
    {
      "id": "dc529a4420260128213926",
      "shard": "shard_1.json",
      "title": "Lời hào bí ẩn: Ví dụ thực tế 2026",
      "category": "Kinh Dịch & Dự Đoán",
      "tags": [
        "autonomous",
        "hyper-depth",
        "agent-25"
      ],
      "created_at": "2026-01-28T21:39:26.581226"
    },
    {
      "id": "903df62d20260128213927",
      "shard": "shard_1.json",
      "title": "Ứng dụng Kinh Dịch trong tài chính: Dữ liệu gốc từ cổ tịch/papers",
      "category": "Kinh Dịch & Dự Đoán",
      "tags": [
        "autonomous",
        "hyper-depth",
        "agent-34"
      ],
      "created_at": "2026-01-28T21:39:27.816710"
    },
    {
      "id": "697ff11820260128213928",
      "shard": "shard_1.json",
      "title": "Kinh Dịch và vật lý lượng tử: Ví dụ thực tế 2026",
      "category": "Kinh Dịch & Dự Đoán",
      "tags": [
        "autonomous",
        "hyper-depth",
        "agent-8"
      ],
      "created_at": "2026-01-28T21:39:28.332148"
    },
    {
      "id": "9d7e0f9220260128213929",
      "shard": "shard_1.json",
      "title": "Huyền Không Đại Quái: Giải pháp tối ưu",
      "category": "Kinh Dịch & Dự Đoán",
      "tags": [
        "autonomous",
        "hyper-depth",
        "agent-41"
      ],
      "created_at": "2026-01-28T21:39:29.042104"
    },
    {
      "id": "9888ffad20260128213930",
      "shard": "shard_1.json",
      "title": "Kinh Dịch và vật lý lượng tử: Hướng dẫn chi thực",
      "category": "Kinh Dịch & Dự Đoán",
      "tags": [
        "autonomous",
        "hyper-depth",
        "agent-45"
      ],
      "created_at": "2026-01-28T21:39:30.578539"
    },
    {
      "id": "8ec0463520260128213931",
      "shard": "shard_1.json",
      "title": "Tế lễ và Kinh Dịch: Dữ liệu gốc từ cổ tịch/papers",
      "category": "Kinh Dịch & Dự Đoán",
      "tags": [
        "autonomous",
        "hyper-depth",
        "agent-2"
      ],
      "created_at": "2026-01-28T21:39:31.011303"
    },
    {
      "id": "e41568fb20260128213931",
      "shard": "shard_1.json",
      "title": "Tế lễ và Kinh Dịch: Phân tích rủi ro",
      "category": "Kinh Dịch & Dự Đoán",
      "tags": [
        "autonomous",
        "hyper-depth",
        "agent-40"
      ],
      "created_at": "2026-01-28T21:39:31.605149"
    },
    {
      "id": "65d433c120260128213941",
      "shard": "shard_1.json",
      "title": "Kinh Dịch và vật lý lượng tử: Giải pháp tối ưu",
      "category": "Kinh Dịch & Dự Đoán",
      "tags": [
        "autonomous",
        "hyper-depth",
        "agent-41"
      ],
      "created_at": "2026-01-28T21:39:41.810055"
    },
    {
      "id": "97ecb7e620260128213942",
      "shard": "shard_1.json",
      "title": "Trạch Cát theo Kinh Dịch: Bí quyết thực thi nhanh",
      "category": "Kinh Dịch & Dự Đoán",
      "tags": [
        "autonomous",
        "hyper-depth",
        "agent-43"
      ],
      "created_at": "2026-01-28T21:39:42.315488"
    },
    {
      "id": "3b4563f020260128213944",
      "shard": "shard_1.json",
      "title": "Lục Hào chuyên sâu: Ứng dụng sâu",
      "category": "Kinh Dịch & Dự Đoán",
      "tags": [
        "autonomous",
        "hyper-depth",
        "agent-47"
      ],
      "created_at": "2026-01-28T21:39:44.540890"
    },
    {
      "id": "3e54cb9e20260128213944",
      "shard": "shard_1.json",
      "title": "Trạch Cát theo Kinh Dịch: Ứng dụng sâu",
      "category": "Kinh Dịch & Dự Đoán",
      "tags": [
        "autonomous",
        "hyper-depth",
        "agent-44"
      ],
      "created_at": "2026-01-28T21:39:44.697802"
    },
    {
      "id": "107c546b20260128213944",
      "shard": "shard_1.json",
      "title": "Lục Hào chuyên sâu: Ví dụ thực tế 2026",
      "category": "Kinh Dịch & Dự Đoán",
      "tags": [
        "autonomous",
        "hyper-depth",
        "agent-44"
      ],
      "created_at": "2026-01-28T21:39:44.704728"
    },
    {
      "id": "c11d567920260128213944",
      "shard": "shard_1.json",
      "title": "Lời hào bí ẩn: Hướng dẫn chi thực",
      "category": "Kinh Dịch & Dự Đoán",
      "tags": [
        "autonomous",
        "hyper-depth",
        "agent-3"
      ],
      "created_at": "2026-01-28T21:39:44.852581"
    },
    {
      "id": "1778729720260128213945",
      "shard": "shard_1.json",
      "title": "Mai Hoa Dịch Số nâng cao: Phân tích rủi ro",
      "category": "Kinh Dịch & Dự Đoán",
      "tags": [
        "autonomous",
        "hyper-depth",
        "agent-24"
      ],
      "created_at": "2026-01-28T21:39:45.383695"
    },
    {
      "id": "33ff447720260128213948",
      "shard": "shard_1.json",
      "title": "Dịch học và thuật toán AI: Case study hiếm",
      "category": "Kinh Dịch & Dự Đoán",
      "tags": [
        "autonomous",
        "hyper-depth",
        "agent-47"
      ],
      "created_at": "2026-01-28T21:39:48.221571"
    },
    {
      "id": "b432c5ba20260128213949",
      "shard": "shard_1.json",
      "title": "Mai Hoa Dịch Số nâng cao: Case study hiếm",
      "category": "Kinh Dịch & Dự Đoán",
      "tags": [
        "autonomous",
        "hyper-depth",
        "agent-18"
      ],
      "created_at": "2026-01-28T21:39:49.083666"
    },
    {
      "id": "2023802e20260128213949",
      "shard": "shard_1.json",
      "title": "Huyền Không Đại Quái: Hướng dẫn chi thực",
      "category": "Kinh Dịch & Dự Đoán",
      "tags": [
        "autonomous",
        "hyper-depth",
        "agent-37"
      ],
      "created_at": "2026-01-28T21:39:49.252722"
    },
    {
      "id": "385a704820260128213949",
      "shard": "shard_1.json",
      "title": "64 Quẻ và biến hóa: Phân tích rủi ro",
      "category": "Kinh Dịch & Dự Đoán",
      "tags": [
        "autonomous",
        "hyper-depth",
        "agent-12"
      ],
      "created_at": "2026-01-28T21:39:49.424353"
    },
    {
      "id": "691ecd0b20260128214000",
      "shard": "shard_1.json",
      "title": "Mai Hoa Dịch Số nâng cao: Ví dụ thực tế 2026",
      "category": "Kinh Dịch & Dự Đoán",
      "tags": [
        "autonomous",
        "hyper-depth",
        "agent-24"
      ],
      "created_at": "2026-01-28T21:40:00.448793"
    },
    {
      "id": "b9289a3520260128214000",
      "shard": "shard_1.json",
      "title": "Ứng dụng Kinh Dịch trong tài chính: Hướng dẫn chi thực",
      "category": "Kinh Dịch & Dự Đoán",
      "tags": [
        "autonomous",
        "hyper-depth",
        "agent-31"
      ],
      "created_at": "2026-01-28T21:40:00.996953"
    },
    {
      "id": "3a7fc96020260128214004",
      "shard": "shard_1.json",
      "title": "Kinh Dịch và tâm lý học hiện đại: Phân tích rủi ro",
      "category": "Kinh Dịch & Dự Đoán",
      "tags": [
        "autonomous",
        "hyper-depth",
        "agent-34"
      ],
      "created_at": "2026-01-28T21:40:04.568430"
    },
    {
      "id": "e66b469720260128214004",
      "shard": "shard_1.json",
      "title": "Ứng dụng Kinh Dịch trong tài chính: Giải pháp tối ưu",
      "category": "Kinh Dịch & Dự Đoán",
      "tags": [
        "autonomous",
        "hyper-depth",
        "agent-23"
      ],
      "created_at": "2026-01-28T21:40:04.714755"
    },
    {
      "id": "e3c55ac220260128214005",
      "shard": "shard_1.json",
      "title": "Trạch Cát theo Kinh Dịch: Ví dụ thực tế 2026",
      "category": "Kinh Dịch & Dự Đoán",
      "tags": [
        "autonomous",
        "hyper-depth",
        "agent-32"
      ],
      "created_at": "2026-01-28T21:40:05.183416"
    },
    {
      "id": "686ea4b420260128214005",
      "shard": "shard_1.json",
      "title": "Lời hào bí ẩn: Bí quyết thực thi nhanh",
      "category": "Kinh Dịch & Dự Đoán",
      "tags": [
        "autonomous",
        "hyper-depth",
        "agent-36"
      ],
      "created_at": "2026-01-28T21:40:05.795766"
    },
    {
      "id": "8b05164120260128214006",
      "shard": "shard_1.json",
      "title": "Trạch Cát theo Kinh Dịch: Giải pháp tối ưu",
      "category": "Kinh Dịch & Dự Đoán",
      "tags": [
        "autonomous",
        "hyper-depth",
        "agent-2"
      ],
      "created_at": "2026-01-28T21:40:06.683730"
    },
    {
      "id": "509e50a520260128214006",
      "shard": "shard_1.json",
      "title": "Lục Hào chuyên sâu: Case study hiếm",
      "category": "Kinh Dịch & Dự Đoán",
      "tags": [
        "autonomous",
        "hyper-depth",
        "agent-19"
      ],
      "created_at": "2026-01-28T21:40:06.941019"
    },
    {
      "id": "91195b6e20260128214007",
      "shard": "shard_1.json",
      "title": "Huyền Không Đại Quái: Phân tích rủi ro",
      "category": "Kinh Dịch & Dự Đoán",
      "tags": [
        "autonomous",
        "hyper-depth",
        "agent-21"
      ],
      "created_at": "2026-01-28T21:40:07.087771"
    },
    {
      "id": "29b7438720260128214007",
      "shard": "shard_1.json",
      "title": "Mai Hoa Dịch Số nâng cao: Giải pháp tối ưu",
      "category": "Kinh Dịch & Dự Đoán",
      "tags": [
        "autonomous",
        "hyper-depth",
        "agent-27"
      ],
      "created_at": "2026-01-28T21:40:07.150297"
    },
    {
      "id": "a12a374420260128214025",
      "shard": "shard_1.json",
      "title": "Tế lễ và Kinh Dịch: Giải pháp tối ưu",
      "category": "Kinh Dịch & Dự Đoán",
      "tags": [
        "autonomous",
        "hyper-depth",
        "agent-18"
      ],
      "created_at": "2026-01-28T21:40:25.671712"
    },
    {
      "id": "c5d6542720260128214031",
      "shard": "shard_1.json",
      "title": "Dịch học và thuật toán AI: Hướng dẫn chi thực",
      "category": "Kinh Dịch & Dự Đoán",
      "tags": [
        "autonomous",
        "hyper-depth",
        "agent-18"
      ],
      "created_at": "2026-01-28T21:40:31.409225"
    },
    {
      "id": "af1b513420260128214032",
      "shard": "shard_1.json",
      "title": "Huyền Không Đại Quái: Bí quyết thực thi nhanh",
      "category": "Kinh Dịch & Dự Đoán",
      "tags": [
        "autonomous",
        "hyper-depth",
        "agent-4"
      ],
      "created_at": "2026-01-28T21:40:32.471561"
    },
    {
      "id": "82b1c0fa20260128214034",
      "shard": "shard_1.json",
      "title": "Trạch Cát theo Kinh Dịch: Phân tích rủi ro",
      "category": "Kinh Dịch & Dự Đoán",
      "tags": [
        "autonomous",
        "hyper-depth",
        "agent-45"
      ],
      "created_at": "2026-01-28T21:40:34.031960"
    },
    {
      "id": "2b91ca5520260128214037",
      "shard": "shard_1.json",
      "title": "Tế lễ và Kinh Dịch: Case study hiếm",
      "category": "Kinh Dịch & Dự Đoán",
      "tags": [
        "autonomous",
        "hyper-depth",
        "agent-21"
      ],
      "created_at": "2026-01-28T21:40:37.670191"
    },
    {
      "id": "18b7028820260128150719",
      "shard": "shard_1.json",
      "title": "64 Quẻ và biến hóa: Ứng dụng sâu",
      "category": "Kinh Dịch & Dự Đoán",
      "tags": [
        "autonomous",
        "hyper-depth",
        "agent-10"
      ],
      "created_at": "2026-01-28T15:07:19.734844"
    },
    {
      "id": "69ff73c320260128150721",
      "shard": "shard_1.json",
      "title": "Tế lễ và Kinh Dịch: Ví dụ thực tế 2026",
      "category": "Kinh Dịch & Dự Đoán",
      "tags": [
        "autonomous",
        "hyper-depth",
        "agent-42"
      ],
      "created_at": "2026-01-28T15:07:21.402298"
    },
    {
      "id": "05004ef320260128150722",
      "shard": "shard_1.json",
      "title": "Tượng quẻ thực tế: Ví dụ thực tế 2026",
      "category": "Kinh Dịch & Dự Đoán",
      "tags": [
        "autonomous",
        "hyper-depth",
        "agent-4"
      ],
      "created_at": "2026-01-28T15:07:22.691019"
    },
    {
      "id": "71b3276920260128150726",
      "shard": "shard_1.json",
      "title": "Mai Hoa Dịch Số nâng cao: Bí quyết thực thi nhanh",
      "category": "Kinh Dịch & Dự Đoán",
      "tags": [
        "autonomous",
        "hyper-depth",
        "agent-1"
      ],
      "created_at": "2026-01-28T15:07:26.734648"
    },
    {
      "id": "10f31c6220260128150727",
      "shard": "shard_1.json",
      "title": "Trạch Cát theo Kinh Dịch: Hướng dẫn chi thực",
      "category": "Kinh Dịch & Dự Đoán",
      "tags": [
        "autonomous",
        "hyper-depth",
        "agent-20"
      ],
      "created_at": "2026-01-28T15:07:27.680206"
    },
    {
      "id": "e9e47a4120260128150728",
      "shard": "shard_1.json",
      "title": "Kinh Dịch và tâm lý học hiện đại: Case study hiếm",
      "category": "Kinh Dịch & Dự Đoán",
      "tags": [
        "autonomous",
        "hyper-depth",
        "agent-17"
      ],
      "created_at": "2026-01-28T15:07:28.204486"
    },
    {
      "id": "95a5569520260128150729",
      "shard": "shard_1.json",
      "title": "Tượng quẻ thực tế: Ứng dụng sâu",
      "category": "Kinh Dịch & Dự Đoán",
      "tags": [
        "autonomous",
        "hyper-depth",
        "agent-11"
      ],
      "created_at": "2026-01-28T15:07:29.527492"
    },
    {
      "id": "de0947d220260128150818",
      "shard": "shard_1.json",
      "title": "Lời hào bí ẩn: Giải pháp tối ưu",
      "category": "Kinh Dịch & Dự Đoán",
      "tags": [
        "autonomous",
        "hyper-depth",
        "agent-20"
      ],
      "created_at": "2026-01-28T15:08:18.859917"
    },
    {
      "id": "6e4e842b20260128150824",
      "shard": "shard_1.json",
      "title": "Kinh Dịch và vật lý lượng tử: Bí quyết thực thi nhanh",
      "category": "Kinh Dịch & Dự Đoán",
      "tags": [
        "autonomous",
        "hyper-depth",
        "agent-31"
      ],
      "created_at": "2026-01-28T15:08:24.133623"
    },
    {
      "id": "b105061120260128150826",
      "shard": "shard_1.json",
      "title": "Tượng quẻ thực tế: Dữ liệu gốc từ cổ tịch/papers",
      "category": "Kinh Dịch & Dự Đoán",
      "tags": [
        "autonomous",
        "hyper-depth",
        "agent-30"
      ],
      "created_at": "2026-01-28T15:08:26.388473"
    },
    {
      "id": "5ca6fbf320260128150826",
      "shard": "shard_1.json",
      "title": "Tế lễ và Kinh Dịch: Hướng dẫn chi thực",
      "category": "Kinh Dịch & Dự Đoán",
      "tags": [
        "autonomous",
        "hyper-depth",
        "agent-14"
      ],
      "created_at": "2026-01-28T15:08:26.498491"
    },
    {
      "id": "d8732e3820260128150829",
      "shard": "shard_1.json",
      "title": "Kinh Dịch và tâm lý học hiện đại: Giải pháp tối ưu",
      "category": "Kinh Dịch & Dự Đoán",
      "tags": [
        "autonomous",
        "hyper-depth",
        "agent-16"
      ],
      "created_at": "2026-01-28T15:08:29.362739"
    },
    {
      "id": "87259c8420260128150829",
      "shard": "shard_1.json",
      "title": "Dịch học và thuật toán AI: Bí quyết thực thi nhanh",
      "category": "Kinh Dịch & Dự Đoán",
      "tags": [
        "autonomous",
        "hyper-depth",
        "agent-1"
      ],
      "created_at": "2026-01-28T15:08:29.753031"
    },
    {
      "id": "158a719220260128150833",
      "shard": "shard_1.json",
      "title": "Kinh Dịch và vật lý lượng tử: Case study hiếm",
      "category": "Kinh Dịch & Dự Đoán",
      "tags": [
        "autonomous",
        "hyper-depth",
        "agent-3"
      ],
      "created_at": "2026-01-28T15:08:33.701158"
    },
    {
      "id": "771c885820260128150833",
      "shard": "shard_1.json",
      "title": "Tượng quẻ thực tế: Phân tích rủi ro",
      "category": "Kinh Dịch & Dự Đoán",
      "tags": [
        "autonomous",
        "hyper-depth",
        "agent-11"
      ],
      "created_at": "2026-01-28T15:08:33.886237"
    },
    {
      "id": "f76e4c4b20260128150836",
      "shard": "shard_1.json",
      "title": "Ứng dụng Kinh Dịch trong tài chính: Phân tích rủi ro",
      "category": "Kinh Dịch & Dự Đoán",
      "tags": [
        "autonomous",
        "hyper-depth",
        "agent-23"
      ],
      "created_at": "2026-01-28T15:08:36.308197"
    },
    {
      "id": "10bdac1620260128150838",
      "shard": "shard_1.json",
      "title": "Dịch học và thuật toán AI: Phân tích rủi ro",
      "category": "Kinh Dịch & Dự Đoán",
      "tags": [
        "autonomous",
        "hyper-depth",
        "agent-32"
      ],
      "created_at": "2026-01-28T15:08:38.062459"
    },
    {
      "id": "ee1c665820260128150838",
      "shard": "shard_1.json",
      "title": "Mai Hoa Dịch Số nâng cao: Hướng dẫn chi thực",
      "category": "Kinh Dịch & Dự Đoán",
      "tags": [
        "autonomous",
        "hyper-depth",
        "agent-29"
      ],
      "created_at": "2026-01-28T15:08:38.875166"
    },
    {
      "id": "f681472f20260128150841",
      "shard": "shard_1.json",
      "title": "Trạch Cát theo Kinh Dịch: Case study hiếm",
      "category": "Kinh Dịch & Dự Đoán",
      "tags": [
        "autonomous",
        "hyper-depth",
        "agent-50"
      ],
      "created_at": "2026-01-28T15:08:41.756092"
    },
    {
      "id": "abb7e6ca20260128150925",
      "shard": "shard_1.json",
      "title": "Mai Hoa Dịch Số nâng cao: Dữ liệu gốc từ cổ tịch/papers",
      "category": "Kinh Dịch & Dự Đoán",
      "tags": [
        "autonomous",
        "hyper-depth",
        "agent-14"
      ],
      "created_at": "2026-01-28T15:09:25.036570"
    },
    {
      "id": "077b6c6c20260128150931",
      "shard": "shard_1.json",
      "title": "Huyền Không Đại Quái: Case study hiếm",
      "category": "Kinh Dịch & Dự Đoán",
      "tags": [
        "autonomous",
        "hyper-depth",
        "agent-27"
      ],
      "created_at": "2026-01-28T15:09:31.387454"
    },
    {
      "id": "2bd27ff220260128150932",
      "shard": "shard_1.json",
      "title": "Lục Hào chuyên sâu: Giải pháp tối ưu",
      "category": "Kinh Dịch & Dự Đoán",
      "tags": [
        "autonomous",
        "hyper-depth",
        "agent-29"
      ],
      "created_at": "2026-01-28T15:09:32.389104"
    },
    {
      "id": "dfbb3d8620260128151013",
      "shard": "shard_1.json",
      "title": "Lời hào bí ẩn: Case study hiếm",
      "category": "Kinh Dịch & Dự Đoán",
      "tags": [
        "autonomous",
        "hyper-depth",
        "agent-10"
      ],
      "created_at": "2026-01-28T15:10:13.991908"
    }
  ],
  "stats": {
    "total": 65,
    "categories": {
      "Công Nghệ Mới & Tương Lai": 5,
      "Kinh Dịch & Dự Đoán": 60
    }
  }
}